automcp/__init__.py
automcp/cli.py
automcp/adapters/__init__.py
automcp/adapters/crewai.py
automcp/adapters/langgraph.py
automcp/adapters/llamaindex.py
automcp/adapters/mcp_agent.py
automcp/adapters/openai.py
automcp/adapters/pydantic.py
automcp/adapters/utils.py
automcp/cli_templates/framework_config.yaml
automcp/cli_templates/run_mcp.py.template
iflow_mcp_napthaai_automcp-0.1.1.dist-info/METADATA
iflow_mcp_napthaai_automcp-0.1.1.dist-info/WHEEL
iflow_mcp_napthaai_automcp-0.1.1.dist-info/entry_points.txt
iflow_mcp_napthaai_automcp-0.1.1.dist-info/licenses/LICENSE
iflow_mcp_napthaai_automcp-0.1.1.dist-info/RECORD
