Metadata-Version: 2.4
Name: iflow-mcp_NapthaAI_automcp
Version: 0.1.1
Summary: Convert tool, agents and orchestrators from existing agent frameworks to MCP servers
Project-URL: Homepage, https://github.com/NapthaAI/automcp
Author-email: Richard Blythman <richard@naptha.ai>
License:                                  Apache License
License-File: LICENSE
Requires-Python: >=3.10
Requires-Dist: mcp>=1.6.0
Requires-Dist: pydantic>=2.11.1
Requires-Dist: python-dotenv>=1.0.0
Requires-Dist: toml>=0.10.0
